[
  {
    "code":"600667",
    "name":"太极实业",
    "industry":"半导体",
    "close":25.31,
    "yaogu_score":9,
    "yiziban":1,
    "streak":2,
    "ret_today":10.0,
    "seal":1.0,
    "vol_ratio":0.06
  },
  {
    "code":"605366",
    "name":"宏柏新材",
    "industry":"化工原料",
    "close":13.07,
    "yaogu_score":9,
    "yiziban":1,
    "streak":3,
    "ret_today":10.0,
    "seal":1.0,
    "vol_ratio":0.57
  },
  {
    "code":"002674",
    "name":"兴业科技",
    "industry":"纺织",
    "close":26.21,
    "yaogu_score":9,
    "yiziban":1,
    "streak":5,
    "ret_today":10.0,
    "seal":1.0,
    "vol_ratio":0.3
  },
  {
    "code":"603989",
    "name":"艾华集团",
    "industry":"元器件",
    "close":53.75,
    "yaogu_score":6,
    "yiziban":0,
    "streak":2,
    "ret_today":10.0,
    "seal":1.0,
    "vol_ratio":0.38
  },
  {
    "code":"603929",
    "name":"亚翔集成",
    "industry":"装修装饰",
    "close":255.07,
    "yaogu_score":6,
    "yiziban":0,
    "streak":2,
    "ret_today":10.0,
    "seal":1.0,
    "vol_ratio":0.4
  },
  {
    "code":"603678",
    "name":"火炬电子",
    "industry":"元器件",
    "close":75.13,
    "yaogu_score":6,
    "yiziban":0,
    "streak":2,
    "ret_today":10.0,
    "seal":1.0,
    "vol_ratio":0.33
  },
  {
    "code":"603115",
    "name":"海星股份",
    "industry":"铝",
    "close":131.33,
    "yaogu_score":6,
    "yiziban":0,
    "streak":2,
    "ret_today":10.0,
    "seal":1.0,
    "vol_ratio":0.58
  },
  {
    "code":"600584",
    "name":"长电科技",
    "industry":"半导体",
    "close":104.17,
    "yaogu_score":6,
    "yiziban":0,
    "streak":2,
    "ret_today":10.0,
    "seal":1.0,
    "vol_ratio":0.63
  },
  {
    "code":"000818",
    "name":"航锦科技",
    "industry":"化工原料",
    "close":14.81,
    "yaogu_score":6,
    "yiziban":0,
    "streak":2,
    "ret_today":10.0,
    "seal":1.0,
    "vol_ratio":0.95
  },
  {
    "code":"000823",
    "name":"超声电子",
    "industry":"元器件",
    "close":25.87,
    "yaogu_score":5,
    "yiziban":0,
    "streak":2,
    "ret_today":10.0,
    "seal":1.0,
    "vol_ratio":0.57
  },
  {
    "code":"603986",
    "name":"兆易创新",
    "industry":"半导体",
    "close":775.21,
    "yaogu_score":5,
    "yiziban":0,
    "streak":2,
    "ret_today":9.9,
    "seal":1.0,
    "vol_ratio":1.17
  },
  {
    "code":"002254",
    "name":"泰和新材",
    "industry":"化纤",
    "close":20.17,
    "yaogu_score":5,
    "yiziban":0,
    "streak":2,
    "ret_today":10.0,
    "seal":1.0,
    "vol_ratio":1.5
  },
  {
    "code":"002484",
    "name":"江海股份",
    "industry":"元器件",
    "close":111.02,
    "yaogu_score":5,
    "yiziban":0,
    "streak":1,
    "ret_today":10.0,
    "seal":1.0,
    "vol_ratio":0.41
  },
  {
    "code":"603067",
    "name":"振华股份",
    "industry":"化工原料",
    "close":46.38,
    "yaogu_score":5,
    "yiziban":0,
    "streak":2,
    "ret_today":10.0,
    "seal":1.0,
    "vol_ratio":1.31
  },
  {
    "code":"600888",
    "name":"新疆众和",
    "industry":"铝",
    "close":16.12,
    "yaogu_score":4,
    "yiziban":0,
    "streak":1,
    "ret_today":10.0,
    "seal":1.0,
    "vol_ratio":0.71
  },
  {
    "code":"603661",
    "name":"恒林股份",
    "industry":"家居用品",
    "close":37.3,
    "yaogu_score":4,
    "yiziban":0,
    "streak":1,
    "ret_today":10.0,
    "seal":1.0,
    "vol_ratio":0.62
  },
  {
    "code":"000811",
    "name":"冰轮环境",
    "industry":"工程机械",
    "close":53.52,
    "yaogu_score":4,
    "yiziban":0,
    "streak":2,
    "ret_today":9.8,
    "seal":1.0,
    "vol_ratio":1.51
  },
  {
    "code":"002990",
    "name":"盛视科技",
    "industry":"软件服务",
    "close":72.6,
    "yaogu_score":4,
    "yiziban":0,
    "streak":2,
    "ret_today":10.0,
    "seal":1.0,
    "vol_ratio":0.84
  },
  {
    "code":"600903",
    "name":"贵州燃气",
    "industry":"供气供热",
    "close":7.99,
    "yaogu_score":3,
    "yiziban":0,
    "streak":1,
    "ret_today":10.1,
    "seal":1.0,
    "vol_ratio":1.0
  },
  {
    "code":"600186",
    "name":"莲花控股",
    "industry":"食品",
    "close":15.6,
    "yaogu_score":3,
    "yiziban":0,
    "streak":1,
    "ret_today":10.0,
    "seal":1.0,
    "vol_ratio":0.67
  },
  {
    "code":"600176",
    "name":"中国巨石",
    "industry":"玻璃",
    "close":70.8,
    "yaogu_score":3,
    "yiziban":0,
    "streak":2,
    "ret_today":9.2,
    "seal":0.993,
    "vol_ratio":1.36
  },
  {
    "code":"603500",
    "name":"祥和实业",
    "industry":"运输设备",
    "close":12.96,
    "yaogu_score":3,
    "yiziban":0,
    "streak":1,
    "ret_today":10.0,
    "seal":1.0,
    "vol_ratio":0.4
  },
  {
    "code":"002980",
    "name":"华盛昌",
    "industry":"电器仪表",
    "close":123.83,
    "yaogu_score":3,
    "yiziban":0,
    "streak":1,
    "ret_today":10.0,
    "seal":1.0,
    "vol_ratio":0.62
  },
  {
    "code":"603713",
    "name":"密尔克卫",
    "industry":"仓储物流",
    "close":75.65,
    "yaogu_score":3,
    "yiziban":0,
    "streak":2,
    "ret_today":10.0,
    "seal":1.0,
    "vol_ratio":2.41
  },
  {
    "code":"603800",
    "name":"洪田股份",
    "industry":"专用机械",
    "close":84.95,
    "yaogu_score":3,
    "yiziban":0,
    "streak":1,
    "ret_today":10.0,
    "seal":1.0,
    "vol_ratio":0.7
  },
  {
    "code":"002080",
    "name":"中材科技",
    "industry":"玻璃",
    "close":92.93,
    "yaogu_score":3,
    "yiziban":0,
    "streak":2,
    "ret_today":10.0,
    "seal":1.0,
    "vol_ratio":0.73
  },
  {
    "code":"002068",
    "name":"黑猫股份",
    "industry":"化工原料",
    "close":14.83,
    "yaogu_score":3,
    "yiziban":0,
    "streak":1,
    "ret_today":10.0,
    "seal":1.0,
    "vol_ratio":1.65
  },
  {
    "code":"002046",
    "name":"国机精工",
    "industry":"机械基件",
    "close":75.41,
    "yaogu_score":3,
    "yiziban":0,
    "streak":2,
    "ret_today":7.8,
    "seal":0.98,
    "vol_ratio":2.04
  },
  {
    "code":"002025",
    "name":"航天电器",
    "industry":"元器件",
    "close":73.27,
    "yaogu_score":3,
    "yiziban":0,
    "streak":2,
    "ret_today":10.0,
    "seal":1.0,
    "vol_ratio":2.35
  },
  {
    "code":"605376",
    "name":"博迁新材",
    "industry":"小金属",
    "close":246.84,
    "yaogu_score":3,
    "yiziban":0,
    "streak":1,
    "ret_today":10.0,
    "seal":1.0,
    "vol_ratio":0.53
  }
]